{
  "n_pairs": 5000,
  "n_clauses": 19764,
  "coordinate_systems": {
    "alpha": {
      "description": "Arithmetic {0,1,2} \u2014 Q1 Mode",
      "values": [
        0,
        1,
        2
      ]
    },
    "eta": {
      "description": "Geometric {-1,+1,\u221a2} \u2014 Q2 Domain",
      "values": [
        -1,
        1,
        1.414214
      ]
    },
    "omega": {
      "description": "Transcendental {2,\u221a2,2^\u221a2} \u2014 Q3 Object",
      "values": [
        2,
        1.414214,
        2.665144
      ]
    }
  },
  "correlations_with_embedding_distance": {
    "uniform_count": 0.0662,
    "alpha_weighted": 0.0386,
    "eta_weighted": 0.0501,
    "omega_weighted": 0.0384,
    "mixed_AGT": 0.0384
  },
  "per_axis_correlations": {
    "alpha_q1": 0.0112,
    "eta_q2": 0.0231,
    "omega_q3": 0.0606,
    "uniform_q1": 0.0218,
    "uniform_q2": 0.0452,
    "uniform_q3": 0.0513
  },
  "interpretation": {
    "best_predictor": "uniform_count",
    "best_correlation": 0.0662,
    "mixed_beats_uniform": false,
    "improvement": -0.0278
  }
}